ai_emotion-1.0.1.dist-info/METADATA
ai_emotion-1.0.1.dist-info/WHEEL
ai_emotion-1.0.1.dist-info/licenses/LICENSE
ai_emotion/__init__.py
ai_emotion/complex_emotion.py
ai_emotion/conversion.py
ai_emotion/description.py
ai_emotion/emotion_vector.py
ai_emotion/generation.py
ai_emotion/gpt.py
ai_emotion/simple_emotion.py
ai_emotion/transition.py
ai_emotion-1.0.1.dist-info/RECORD
