Metadata-Version: 2.1
Name: ai_emotion
Version: 1.0.1
Summary: Representation of emotional state for use in AI agents.
Author-Email: Matt Zhang <set.stun@gmail.com>
License: MIT
Project-URL: Homepage, https://github.com/MattUnderscoreZhang/AIEmotion
Requires-Python: >=3.8
Requires-Dist: py-gpt-interface>=0.3.2
Requires-Dist: pandas>=2.0.3
Requires-Dist: numpy>=1.24.4
Requires-Dist: rich>=13.7.0
